puccini/__init__.py
puccini/go.py
puccini/libpuccini.so
puccini/tosca.py
puccini-0.21.0.dist-info/METADATA
puccini-0.21.0.dist-info/WHEEL
puccini-0.21.0.dist-info/top_level.txt
puccini-0.21.0.dist-info/RECORD
