Metadata-Version: 2.1
Name: puccini
Version: 0.21.0
Summary: Puccini
Home-page: https://github.com/tliron/puccini
Download-URL: https://github.com/tliron/puccini/releases
Author: Tal Liron
Author-email: tal.liron@gmail.com
License: Apache License 2.0
Classifier: Development Status :: 4 - Beta
Classifier: Intended Audience :: Developers
Classifier: License :: OSI Approved :: Apache Software License
Requires-Dist: ard
